{
    "tools": [
        {
            "type": "reconnaissance",
            "owner": "projectdiscovery",
            "repo": "subfinder",
            "url": "https://github.com/projectdiscovery/subfinder"
        },
        {
            "type": "reconnaissance",
            "owner": "projectdiscovery",
            "repo": "httpx",
            "url": "https://github.com/projectdiscovery/httpx"
        },
        {
            "type": "reconnaissance",
            "owner": "OWASP",
            "repo": "amass",
            "url": "https://github.com/OWASP/Amass"
        },
        {
            "type": "network",
            "owner": "tomnomnom",
            "repo": "httprobe",
            "url": "https://github.com/tomnomnom/httprobe"
        },
        {
            "type": "network",
            "owner": "projectdiscovery",
            "repo": "dnsx",
            "url": "https://github.com/projectdiscovery/dnsx"
        },
        {
            "type": "web_exploit",
            "owner": "incogbyte",
            "repo": "shosubgo",
            "url": "https://github.com/incogbyte/shosubgo"
        },
        {
            "type": "web_exploit",
            "owner": "ffuf",
            "repo": "ffuf",
            "url": "https://github.com/ffuf/ffuf"
        },
        {
            "type": "network",
            "owner": "nmap",
            "repo": "nmap",
            "url": "https://github.com/nmap/nmap"
        },
        {
            "type": "network",
            "owner": "projectdiscovery",
            "repo": "naabu",
            "url": "https://github.com/projectdiscovery/naabu"
        },
        {
            "type": "network",
            "owner": "robertdavidgraham",
            "repo": "masscan",
            "url": "https://github.com/robertdavidgraham/masscan"
        },
        {
            "type": "web_exploit",
            "owner": "projectdiscovery",
            "repo": "nuclei",
            "url": "https://github.com/projectdiscovery/nuclei"
        },
        {
            "type": "web_exploit",
            "owner": "SNGWN",
            "repo": "burp-suite",
            "url": "https://github.com/SNGWN/Burp-Suite"
        },
        {
            "type": "reverse_engineering",
            "owner": "skylot",
            "repo": "jadx",
            "url": "https://github.com/skylot/jadx"
        },
        {
            "type": "reverse_engineering",
            "owner": "NationalSecurityAgency",
            "repo": "ghidra",
            "url": "https://github.com/NationalSecurityAgency/ghidra"
        },
        {
            "type": "osint",
            "owner": "achillean",
            "repo": "shodan",
            "url": "https://github.com/achillean/shodan-python"
        },
        {
            "type": "osint",
            "owner": "smicallef",
            "repo": "spiderfoot",
            "url": "https://github.com/smicallef/spiderfoot"
        },
        {
            "type": "osint",
            "owner": "MaltegoTech",
            "repo": "maltego",
            "url": "https://github.com/MaltegoTech/maltego-trx"
        },
        {
            "type": "forensic",
            "owner": "sleuthkit",
            "repo": "autopsy",
            "url": "https://github.com/sleuthkit/autopsy"
        },
        {
            "type": "web_exploit",
            "owner": "fuzzdb-project",
            "repo": "fuzzdb",
            "url": "https://github.com/fuzzdb-project/fuzzdb"
        }
    ]
}
